README.md
setup.py
pulumiverse_time/__init__.py
pulumiverse_time/_utilities.py
pulumiverse_time/offset.py
pulumiverse_time/provider.py
pulumiverse_time/pulumi-plugin.json
pulumiverse_time/py.typed
pulumiverse_time/rotating.py
pulumiverse_time/sleep.py
pulumiverse_time/static.py
pulumiverse_time.egg-info/PKG-INFO
pulumiverse_time.egg-info/SOURCES.txt
pulumiverse_time.egg-info/dependency_links.txt
pulumiverse_time.egg-info/not-zip-safe
pulumiverse_time.egg-info/requires.txt
pulumiverse_time.egg-info/top_level.txt