Metadata-Version: 2.1
Name: pulumiverse-time
Version: 0.0.16
Summary: A Pulumi package for creating and managing Time resources
Home-page: https://github.com/pulumiverse/pulumi-time
License: Apache-2.0
Project-URL: Repository, https://github.com/pulumiverse/pulumi-time
Keywords: pulumi time category/utility
Platform: UNKNOWN
Requires-Python: >=3.7
